ncdb_tools/__init__.py
ncdb_tools/constants.py
ncdb_tools/data_dictionary.py
ncdb_tools/database_builder.py
ncdb_tools/dataset_builder.py
ncdb_tools/query.py
ncdb_tools/_internal/__init__.py
ncdb_tools/_internal/sas_parser.py
ncdb_tools-0.1.0.dist-info/METADATA
ncdb_tools-0.1.0.dist-info/WHEEL
ncdb_tools-0.1.0.dist-info/licenses/LICENSE
ncdb_tools-0.1.0.dist-info/RECORD
