Metadata-Version: 2.4
Name: ncdb-tools
Version: 0.1.0
Summary: Tools for processing and analyzing National Cancer Database (NCDB) data
Author: NCDB Tools Contributors
License: MIT
License-File: LICENSE
Keywords: analysis,cancer,database,medical-research,ncdb,parquet
Classifier: Development Status :: 4 - Beta
Classifier: Intended Audience :: Healthcare Industry
Classifier: Intended Audience :: Science/Research
Classifier: License :: OSI Approved :: MIT License
Classifier: Operating System :: OS Independent
Classifier: Programming Language :: Python :: 3
Classifier: Programming Language :: Python :: 3.9
Classifier: Programming Language :: Python :: 3.10
Classifier: Programming Language :: Python :: 3.11
Classifier: Programming Language :: Python :: 3.12
Classifier: Topic :: Scientific/Engineering :: Information Analysis
Classifier: Topic :: Scientific/Engineering :: Medical Science Apps.
Requires-Python: >=3.9
Requires-Dist: click>=8.0.0
Requires-Dist: polars>=0.19.0
Requires-Dist: pyarrow>=10.0.0
Requires-Dist: rich>=10.0.0
Provides-Extra: dev
Requires-Dist: mypy>=1.0.0; extra == 'dev'
Requires-Dist: pytest-cov>=4.0.0; extra == 'dev'
Requires-Dist: pytest>=7.0.0; extra == 'dev'
Requires-Dist: ruff>=0.0.280; extra == 'dev'
